mwdoc/__init__.py
mwdoc/_version.py
mwdoc-0.1.0.dist-info/DESCRIPTION.rst
mwdoc-0.1.0.dist-info/METADATA
mwdoc-0.1.0.dist-info/RECORD
mwdoc-0.1.0.dist-info/WHEEL
mwdoc-0.1.0.dist-info/metadata.json
mwdoc-0.1.0.dist-info/top_level.txt
