Metadata-Version: 2.0
Name: mwdoc
Version: 0.1.0
Summary: Allow to easily version mediawiki pages.
Home-page: https://github.com/jcfr/mwdoc#readme
Author: Jean-Christophe Fillion-Robin
Author-email: jchris.fillionr@kitware.com
License: Apache
Keywords: mediawiki wikipedia
Platform: UNKNOWN
Classifier: Development Status :: 4 - Beta
Classifier: Environment :: Console
Classifier: License :: OSI Approved :: Apache Software License
Classifier: Natural Language :: English
Classifier: Operating System :: OS Independent
Classifier: Programming Language :: Python :: 2
Classifier: Programming Language :: Python :: 2.7
Classifier: Programming Language :: Python :: 3
Classifier: Programming Language :: Python :: 3.3
Classifier: Programming Language :: Python :: 3.4
Classifier: Programming Language :: Python :: 3.5
Classifier: Topic :: Documentation
Classifier: Topic :: Software Development :: Documentation
Requires-Dist: mwclient (>=0.7.0)
